{"/posts/git-hook/":"https://ambersun1234.github.io/git/git-hook/","/posts/git-rebase/":"https://ambersun1234.github.io/git/git-rebase/","/website/website-grpc/":"https://ambersun1234.github.io/website/website-rpc/","/http/networking-osi/":"https://ambersun1234.github.io/network/network-osi/","/network/networking-osi/":"https://ambersun1234.github.io/network/network-osi/","/http/networking-http1/":"https://ambersun1234.github.io/network/network-http1/","/network/networking-http1/":"https://ambersun1234.github.io/network/network-http1/","/posts/golang-channel/":"https://ambersun1234.github.io/random/golang-channel/","/network/networking-basics/":"https://ambersun1234.github.io/network/network-basics/"}